odoo/addons/l10n_it_amount_to_text/README.rst
odoo/addons/l10n_it_amount_to_text/__init__.py
odoo/addons/l10n_it_amount_to_text/__manifest__.py
odoo/addons/l10n_it_amount_to_text/i18n/it.po
odoo/addons/l10n_it_amount_to_text/i18n/l10n_it_amount_to_text.pot
odoo/addons/l10n_it_amount_to_text/models/__init__.py
odoo/addons/l10n_it_amount_to_text/models/res_currency.py
odoo/addons/l10n_it_amount_to_text/readme/CONFIGURE.md
odoo/addons/l10n_it_amount_to_text/readme/CONTRIBUTORS.md
odoo/addons/l10n_it_amount_to_text/readme/DESCRIPTION.md
odoo/addons/l10n_it_amount_to_text/readme/USAGE.md
odoo/addons/l10n_it_amount_to_text/static/description/icon.png
odoo/addons/l10n_it_amount_to_text/static/description/index.html
odoo/addons/l10n_it_amount_to_text/tests/__init__.py
odoo/addons/l10n_it_amount_to_text/tests/test_amount_to_text.py
odoo_addon_l10n_it_amount_to_text-16.0.1.0.0.2.dist-info/METADATA
odoo_addon_l10n_it_amount_to_text-16.0.1.0.0.2.dist-info/WHEEL
odoo_addon_l10n_it_amount_to_text-16.0.1.0.0.2.dist-info/top_level.txt
odoo_addon_l10n_it_amount_to_text-16.0.1.0.0.2.dist-info/RECORD
