Metadata-Version: 2.1
Name: odoo-addon-l10n_it_amount_to_text
Version: 16.0.1.0.0.2
Requires-Python: >=3.10
Requires-Dist: num2words>=0.5.12
Requires-Dist: odoo>=16.0a,<16.1dev
Summary: Localizza le valute in italiano per amount_to_text
Home-page: https://github.com/OCA/l10n-italy
License: AGPL-3
Author: Sergio Zanchetta - Associazione PNLug APS,Ecosoft Co. Ltd,Odoo Community Association (OCA)
Author-email: support@odoo-community.org
Classifier: Programming Language :: Python
Classifier: Framework :: Odoo
Classifier: Framework :: Odoo :: 16.0
Classifier: License :: OSI Approved :: GNU Affero General Public License v3
